arrow/__init__.py
arrow/_version.py
arrow/api.py
arrow/arrow.py
arrow/constants.py
arrow/factory.py
arrow/formatter.py
arrow/locales.py
arrow/parser.py
arrow/py.typed
arrow/util.py
arrow-1.2.1.dist-info/LICENSE
arrow-1.2.1.dist-info/METADATA
arrow-1.2.1.dist-info/WHEEL
arrow-1.2.1.dist-info/top_level.txt
arrow-1.2.1.dist-info/RECORD
