Metadata-Version: 2.1
Name: arrow
Version: 1.2.1
Summary: Better dates & times for Python
Home-page: https://arrow.readthedocs.io
Author: Chris Smith
Author-email: crsmithdev@gmail.com
License: Apache 2.0
Project-URL: Repository, https://github.com/arrow-py/arrow
Project-URL: Bug Reports, https://github.com/arrow-py/arrow/issues
Project-URL: Documentation, https://arrow.readthedocs.io
Keywords: arrow date time datetime timestamp timezone humanize
Platform: UNKNOWN
Classifier: Development Status :: 5 - Production/Stable
Classifier: Intended Audience :: Developers
Classifier: License :: OSI Approved :: Apache Software License
Classifier: Topic :: Software Development :: Libraries :: Python Modules
Classifier: Programming Language :: Python :: 3
Classifier: Programming Language :: Python :: 3 :: Only
Classifier: Programming Language :: Python :: 3.6
Classifier: Programming Language :: Python :: 3.7
Classifier: Programming Language :: Python :: 3.8
Classifier: Programming Language :: Python :: 3.9
Classifier: Programming Language :: Python :: 3.10
Requires-Python: >=3.6
License-File: LICENSE
